hepkit/__init__.py
hepkit/hepData.py
hepkit/hepFormat.py
hepkit/hepIO.py
hepkit/hepPlot.py
hepkit-1.1.5.dist-info/DESCRIPTION.rst
hepkit-1.1.5.dist-info/METADATA
hepkit-1.1.5.dist-info/RECORD
hepkit-1.1.5.dist-info/WHEEL
hepkit-1.1.5.dist-info/metadata.json
hepkit-1.1.5.dist-info/top_level.txt
