Metadata-Version: 2.0
Name: hepkit
Version: 1.1.5
Summary: Tools for performing High Energy Physics analysis with Python
Home-page: https://github.com/sdporzio/HEPKit
Author: Salvatore Davide Porzio
Author-email: porziodavide@gmail.com
License: MIT
Keywords: high energy physics,hep,python,pandas,uproot,pyplot
Platform: UNKNOWN
